pybash/__init__.py
pybash/__main__.py
pybash/hook.py
pybash/transformer.py
pybash-0.3.5.dist-info/LICENSE
pybash-0.3.5.dist-info/METADATA
pybash-0.3.5.dist-info/WHEEL
pybash-0.3.5.dist-info/RECORD
