Metadata-Version: 2.1
Name: PyBash
Version: 0.3.5
Summary: >execute bash commands from python easily
Author: Jay
Author-email: jay.github0@gmail.com
Requires-Python: >=3.9,<4.0
Classifier: Programming Language :: Python :: 3
Classifier: Programming Language :: Python :: 3.9
Classifier: Programming Language :: Python :: 3.10
Classifier: Programming Language :: Python :: 3.11
Classifier: Programming Language :: Python :: 3.12
Provides-Extra: script
Requires-Dist: ideas (>=0.1.5,<0.2.0) ; extra == "script"
Requires-Dist: token-utils (>=0.1.8,<0.2.0)
